bntranslit/__init__.py
bntranslit/bntransliteration.py
bntranslit/utils.py
bntranslit-2.1.0.dist-info/METADATA
bntranslit-2.1.0.dist-info/WHEEL
bntranslit-2.1.0.dist-info/top_level.txt
bntranslit-2.1.0.dist-info/RECORD
