Metadata-Version: 2.1
Name: bntranslit
Version: 2.1.0
Summary: BNTRANSLIT is a deep learning based transliteration app for Bangla word
Home-page: https://github.com/sagorbrur/bntranslit
Author: Sagor Sarker
Author-email: sagorhem3532@gmail.com
License: MIT
Platform: UNKNOWN
Classifier: Programming Language :: Python :: 3
Classifier: License :: OSI Approved :: MIT License
Classifier: Operating System :: OS Independent
Requires-Python: >=3.6
Requires-Dist: numpy
Requires-Dist: wasabi
Requires-Dist: wget
